firecrawl_deepsearch_mcp/__init__.py
firecrawl_deepsearch_mcp/server.py
firecrawl_deepsearch_mcp-0.1.3.dist-info/METADATA
firecrawl_deepsearch_mcp-0.1.3.dist-info/WHEEL
firecrawl_deepsearch_mcp-0.1.3.dist-info/entry_points.txt
firecrawl_deepsearch_mcp-0.1.3.dist-info/RECORD
