Metadata-Version: 2.4
Name: firecrawl-deepsearch-mcp
Version: 0.1.3
Summary: Deepsearch by firecrawl. MCP server
Author-email: Tolik <tolik@svl.services>
Requires-Python: >=3.12
Requires-Dist: bump2version>=1.0.1
Requires-Dist: fastmcp>=2.1.0
Requires-Dist: firecrawl-py>=1.15.0
Requires-Dist: mcp[cli]>=1.6.0
